<?xml version="1.0" encoding="UTF-8"?>
<objects serializationModel="Studio.02.02.00">
	<object class="AudioFile" id="{fabf9b94-63c4-4682-9fbf-01774bf6516a}">
		<property name="assetPath">
			<value>player movement/SwordWhipFencing_BW.59422.wav</value>
		</property>
		<property name="frequencyInKHz">
			<value>96</value>
		</property>
		<property name="channelCount">
			<value>2</value>
		</property>
		<property name="length">
			<value>0.30399999999999999</value>
		</property>
		<relationship name="masterAssetFolder">
			<destination>{c28e1d4f-f9af-4e5f-9cd2-a8a56fd8ed2d}</destination>
		</relationship>
	</object>
</objects>
